beamtrace/__init__.py
beamtrace/tracer.py
beamtrace-0.0.15.dist-info/LICENSE
beamtrace-0.0.15.dist-info/METADATA
beamtrace-0.0.15.dist-info/WHEEL
beamtrace-0.0.15.dist-info/top_level.txt
beamtrace-0.0.15.dist-info/RECORD
