Metadata-Version: 2.1
Name: beamtrace
Version: 0.0.15
Summary: beamtrace for quick ABCD matrix calculations
Home-page: https://git.ligo.org/craig-cahillane/beamtrace
Author: Craig Cahillane
Author-email: craigcahillane@fastmail.com
Classifier: Programming Language :: Python :: 3
Classifier: License :: OSI Approved :: MIT License
Classifier: Operating System :: OS Independent
Requires-Python: >=3.6
License-File: LICENSE
